ds_prod/dataset.py
ds_prod/featureimportance.py
ds_prod/hyperopt.py
ds_prod/preprocessing.py
ds_trainee_prod-0.0.14.dist-info/METADATA
ds_trainee_prod-0.0.14.dist-info/WHEEL
ds_trainee_prod-0.0.14.dist-info/top_level.txt
ds_trainee_prod-0.0.14.dist-info/RECORD
