Metadata-Version: 2.1
Name: ds-trainee-prod
Version: 0.0.14
Summary: My ds trainee project
Author: Natallia Zhamaitsiak
Classifier: Programming Language :: Python :: 3
Classifier: License :: OSI Approved :: MIT License
Classifier: Operating System :: OS Independent
Requires-Python: >=3.6
Requires-Dist: scikit-learn
Requires-Dist: xgboost
Requires-Dist: numpy
Requires-Dist: pandas
Requires-Dist: hyperopt
